<annotation>
	<folder>Mask</folder>
	<filename>0911.jpg</filename>
	<path>C:\Users\Sweet\Desktop\facemask detection\Facemask2\New Masks Dataset\Train\Mask\0911.jpg</path>
	<source>
		<database>Unknown</database>
	</source>
	<size>
		<width>650</width>
		<height>433</height>
		<depth>3</depth>
	</size>
	<segmented>0</segmented>
	<object>
		<name>withmask</name>
		<pose>Unspecified</pose>
		<truncated>0</truncated>
		<difficult>0</difficult>
		<bndbox>
			<xmin>222</xmin>
			<ymin>87</ymin>
			<xmax>457</xmax>
			<ymax>313</ymax>
		</bndbox>
	</object>
</annotation>
