<annotation>
	<folder>Non Mask</folder>
	<filename>208.jpg</filename>
	<path>C:\Users\Sweet\Desktop\facemask detection\Facemask2\New Masks Dataset\Train\Non Mask\208.jpg</path>
	<source>
		<database>Unknown</database>
	</source>
	<size>
		<width>261</width>
		<height>193</height>
		<depth>3</depth>
	</size>
	<segmented>0</segmented>
	<object>
		<name>no_mask</name>
		<pose>Unspecified</pose>
		<truncated>0</truncated>
		<difficult>0</difficult>
		<bndbox>
			<xmin>114</xmin>
			<ymin>42</ymin>
			<xmax>215</xmax>
			<ymax>139</ymax>
		</bndbox>
	</object>
</annotation>
