<annotation>
	<folder>Mask</folder>
	<filename>0205.jpg</filename>
	<path>C:\Users\Sweet\Desktop\facemask detection\Facemask2\New Masks Dataset\Train\Mask\0205.jpg</path>
	<source>
		<database>Unknown</database>
	</source>
	<size>
		<width>480</width>
		<height>640</height>
		<depth>3</depth>
	</size>
	<segmented>0</segmented>
	<object>
		<name>withmask</name>
		<pose>Unspecified</pose>
		<truncated>0</truncated>
		<difficult>0</difficult>
		<bndbox>
			<xmin>202</xmin>
			<ymin>143</ymin>
			<xmax>324</xmax>
			<ymax>279</ymax>
		</bndbox>
	</object>
</annotation>
